{
  "homepage": {
    "abu_yahya_pdf": "مجموع أعمال الشيخ أبي يحيى.pdf",
    "abu_yahya_docx": "مجموع أعمال الشيخ أبي يحيى.docx",
    "atiyatullah_pdf": "مجموع_الشيخ_عطية_الله_الطبعة_الثانية.pdf",
    "atiyatullah_docx": "مجموع_الشيخ_عطية_الله_الطبعة_الثانية.docx"
  },
  "1585-محاورة-الشيخ-أبي-يحيى-الليبي-للشيخ-عطية-الله-حول-ا": {
    "title": "محاورة الشيخ أبي يحيى للشيخ عطية الله حول الثورات العربية",
    "audio": "محاورة الشيخ أبي يحيى الليبي للشيخ عطية الله حول الثورات العربية - صوتي.mp3",
    "video": "محاورة الشيخ أبي يحيى الليبي للشيخ عطية الله حول الثورات العربية - مرئي.mp4"
  },
  "1599-سلسلة-الثقافة-الإسلامية-وَالوعي": {
    "title": "سلسلة الثقافة الإسلامية والوعي (مقدمة)",
    "audio": "سلسلة الثقافة والوعي/الثقافة والوعي 1 - التصور والتصديق - المفاهيم وتصحيحها - الهداية وأسبابها وموانعها.mp3"
  },
  "908-الدرس-الأول": {
    "title": "سلسلة الثقافة الإسلامية والوعي - الدرس الأول: التصور والتصديق وتصحيح المفاهيم",
    "audio": "سلسلة الثقافة والوعي/الثقافة والوعي 1 - التصور والتصديق - المفاهيم وتصحيحها - الهداية وأسبابها وموانعها.mp3"
  },
  "163-الدرس-الثاني": {
    "title": "تأملات في سورة الحجرات - الدرس الثاني",
    "audio": "تأملات في سورة الحجرات - صوتي/tamolat_hojarat_2.mp3"
  },
  "164-الدرس-الثالث": {
    "title": "تأملات في سورة الحجرات - الدرس الثالث",
    "audio": "تأملات في سورة الحجرات - صوتي/tamolat_hojarat_3.mp3"
  },
  "917-الدرس-الرابـع": {
    "title": "سلسلة الثقافة الإسلامية والوعي - الدرس الرابع: العدل والفضل والسبق",
    "audio": "سلسلة الثقافة والوعي/الثقافة والوعي 4 - الدنيا والآخرة - العدل والفضل.mp3"
  },
  "166-الدرس-الخامس": {
    "title": "تأملات في سورة الحجرات - الدرس الخامس",
    "audio": "تأملات في سورة الحجرات - صوتي/tamolat_hojarat_5.mp3"
  },
  "923-الدرس-السادس-والأخير": {
    "title": "سلسلة الثقافة الإسلامية والوعي - الدرس السادس والأخير: مناهج وطرائق التغيير",
    "audio": "سلسلة الثقافة والوعي/الثقافة والوعي 6 - مناهج وطرائق التغيير.mp3"
  },
  "1779-الجُندِيةُ-وَأحْكَامُــهَا": {
    "title": "محاضرة الجندية وأحكامها",
    "audio": "الجندية.mp3",
    "video": "الجندية.mp4"
  },
  "1821-التكفير-والردة": {
    "title": "التكفير والردة",
    "audio": "التكفير.mp3"
  },
  "1840-الموالاة-وَالمعاداة": {
    "title": "شرح رسالة الموالاة والمعاداة",
    "audio": "الموالاة والمعاداة.mp3"
  },
  "936-حصاد-سبع-سنوات-من-الحروب-الصليبية-1300": {
    "title": "إصدار حصاد سبع سنوات من الحروب الصليبية",
    "audio": "كلمات في إصدارات/كلمة الشيخ عطية في إصدار حصاد سبع سنوات من الحروب الصليبية - صوتي.MP3",
    "video": "كلمات في إصدارات/كلمة الشيخ عطية في إصدار حصاد سبع سنوات من الحروب الصليبية - مرئي.mp4"
  },
  "937-ريح-الجنة-3-في-رثاء-الشيخ-أبي-الليث-الليبي-1301": {
    "title": "إصدار ريح الجنة (3) - رثاء أبي الليث الليبي",
    "audio": "كلمات في إصدارات/كلمة الشيخ عطية في إصدار ريح الجنة 3 رثاء أبي الليث الليبي.MP3",
    "video": "كلمات في إصدارات/كلمة الشيخ عطية في إصدار ريح الجنة 3 رثاء أبي الليث الليبي.mp4"
  },
  "938-الغرب-والنفق-المظلم-1305": {
    "title": "إصدار الغرب والنفق المظلم",
    "audio": "كلمات في إصدارات/كلمة الشيخ عطية في إصدار النفق والغرب المظلم.MP3",
    "video": "كلمات في إصدارات/كلمة الشيخ عطية في إصدار النفق والغرب المظلم.mp4"
  },
  "939-لا-تكلف-إلا-نفسك-1306": {
    "title": "إصدار لا تكلف إلا نفسك",
    "audio": "كلمات في إصدارات/كلمة الشيخ عطية ضمن إصدار لا تكلف إلا نفسك.MP3",
    "video": "كلمات في إصدارات/كلمة الشيخ عطية ضمن إصدار لا تكلف إلا نفسك.mp4"
  },
  "1894-فجر-النصر-الوشيك-تراخى-الزمان-على-أمتي": {
    "title": "قصيدة تراخى الزمان على أمتي - بإلقاء الشيخ عطية الله",
    "audio": "قصيدة الشيخ أسامة تراخى الزمان على أمتي بإلقاء الشيخ عطية.MP3",
    "video": "قصيدة الشيخ أسامة تراخى الزمان على أمتي بإلقاء الشيخ عطية.mp4"
  },
  "154-الدُّرَرُ-الحَسَنِيَّةُ؛-شرح-كتاب-السياسة-الشرعية": {
    "title": "الدُّرَرُ الحَسَنِيَّةُ؛ شرح كتاب السياسة الشرعية",
    "audios": [
      "شرح كتاب السياسة الشرعية لشيخ الإسلام ابن تيمية/1.mp3",
      "شرح كتاب السياسة الشرعية لشيخ الإسلام ابن تيمية/2.mp3",
      "شرح كتاب السياسة الشرعية لشيخ الإسلام ابن تيمية/3.mp3",
      "شرح كتاب السياسة الشرعية لشيخ الإسلام ابن تيمية/4.mp3",
      "شرح كتاب السياسة الشرعية لشيخ الإسلام ابن تيمية/5.mp3",
      "شرح كتاب السياسة الشرعية لشيخ الإسلام ابن تيمية/6.mp3",
      "شرح كتاب السياسة الشرعية لشيخ الإسلام ابن تيمية/7.mp3",
      "شرح كتاب السياسة الشرعية لشيخ الإسلام ابن تيمية/8.mp3",
      "شرح كتاب السياسة الشرعية لشيخ الإسلام ابن تيمية/9.mp3",
      "شرح كتاب السياسة الشرعية لشيخ الإسلام ابن تيمية/10.mp3",
      "شرح كتاب السياسة الشرعية لشيخ الإسلام ابن تيمية/11.mp3",
      "شرح كتاب السياسة الشرعية لشيخ الإسلام ابن تيمية/12-1.mp3",
      "شرح كتاب السياسة الشرعية لشيخ الإسلام ابن تيمية/12-2.mp3",
      "شرح كتاب السياسة الشرعية لشيخ الإسلام ابن تيمية/13.mp3",
      "شرح كتاب السياسة الشرعية لشيخ الإسلام ابن تيمية/14.mp3",
      "شرح كتاب السياسة الشرعية لشيخ الإسلام ابن تيمية/15.mp3",
      "شرح كتاب السياسة الشرعية لشيخ الإسلام ابن تيمية/16.mp3",
      "شرح كتاب السياسة الشرعية لشيخ الإسلام ابن تيمية/17.mp3"
    ]
  },
  "165-الدرس-الرابع": {
    "title": "تأملات في سورة الحجرات - الدرس الرابع",
    "audio": "تأملات في سورة الحجرات - صوتي/tamolat_hojarat_4.mp3"
  },
  "167-الدرس-السادس": {
    "title": "تأملات في سورة الحجرات - الدرس السادس",
    "audio": "تأملات في سورة الحجرات - صوتي/tamolat_hojarat_6.mp3"
  },
  "168-الدرس-السابع": {
    "title": "تأملات في سورة الحجرات - الدرس السابع",
    "audio": "تأملات في سورة الحجرات - صوتي/tamolat_hojarat_7.mp3"
  },
  "170-الدرس-الأول-مقدمة-عن-الجهاد---حكمه---شروط-الجهاد": {
    "title": "الدرس الأول: مقدمة عن الجهاد - حكمه - شروط الجهاد",
    "audios": [
      "مختارات من فقه الجهاد من متن الإقناع للحجاوي في الفقه الحنبلي/1- مقدمة عن الجهاد - حكمه - شروط الجهاد.mp3",
      "مختارات من فقه الجهاد من متن الإقناع للحجاوي في الفقه الحنبلي/1- تسجيل آخر مختصر للدرس الأول.mp3"
    ]
  },
  "171-الدرس-الثاني-أفضل-التطوع---حكم-الغزو-مع-الإمام-الف": {
    "title": "الدرس الثاني: أفضل التطوع - حكم الغزو مع الإمام الفاجر - وجوب قتال العدو القريب",
    "audio": "مختارات من فقه الجهاد من متن الإقناع للحجاوي في الفقه الحنبلي/2- أفضل التطوع - حكم الغزو مع الإمام الفاجر - وجوب قتال العدو القريب - حكم الدعوة قبل القتال.mp3"
  },
  "172-الدرس-الثالث-من-يقيم-الجهاد---العمل-إذا-قتل-الأمير": {
    "title": "الدرس الثالث: من يقيم الجهاد",
    "audio": "مختارات من فقه الجهاد من متن الإقناع للحجاوي في الفقه الحنبلي/3- من يقيم الجهاد - العمل إذا قتل الأمير - معنى الرباط - حكم الهجرة.mp3"
  },
  "173-الدرس-الرابع-من-يحرم-قتله---أصناف-الكفار---مسألة-ا": {
    "title": "الدرس الرابع: من يحرم قتله",
    "audio": "مختارات من فقه الجهاد من متن الإقناع للحجاوي في الفقه الحنبلي/4- من يحرم قتله - أصناف الكفار ومسألة المدنيين.mp3"
  },
  "174-الدرس-الخامس-التترس---أحكام-الأسرى": {
    "title": "الدرس الخامس: التترس - أحكام الأسرى",
    "audio": "مختارات من فقه الجهاد من متن الإقناع للحجاوي في الفقه الحنبلي/5- التترس - أحكام الأسرى.mp3"
  },
  "175-الدرس-السادس-تابع-أحكام-الأسرى---حكم-الجاسوس---ما": {
    "title": "الدرس السادس: أحكام الأسرى - حكم الجاسوس",
    "audio": "مختارات من فقه الجهاد من متن الإقناع للحجاوي في الفقه الحنبلي/6- تابع أحكام الأسرى - حكم الجاسوس - ما يلزم الأمير.mp3"
  },
  "176-الدرس-السابع-ما-يلزم-الجيش-تجاه-الأمير---أحكام-الس": {
    "title": "الدرس السابع: ما يلزم الجيش تجاه الأمير - أحكام السلب",
    "audio": "مختارات من فقه الجهاد من متن الإقناع للحجاوي في الفقه الحنبلي/7- ما يلزم الجيش - أحكام السلب.mp3"
  },
  "215-مشاركة-للشيخ-في-برنامج-الشريعة-والحياة-مع-الشيخ-مح": {
    "title": "مشاركة للشيخ في برنامج «الشريعة والحياة» مع الشيخ محمد الددو",
    "audio": "مشاركة للشيخ أبي يحيى في برنامج الشريعة والحياة.mp3",
    "video": "مشاركة للشيخ أبي يحيى في برنامج الشريعة والحياة.mp4"
  },
  "217-خطبة-عيد-الفطر-1426": {
    "title": "خطبة عيد الفطر «1426»",
    "audio": "خطب العيد/خطبة العيد عام 1426 - صوتي.mp3",
    "video": "خطب العيد/خطبة العيد عام 1426.mp4"
  },
  "219-اللقاء-الأول-لمؤسسة-السحاب-مع-الشيخ-بعد-النجاة-من": {
    "title": "اللقاء الأول لمؤسسة السحاب مع الشيخ بعد النجاة من سجن باجرام",
    "audio": "اللقاء الأول لمؤسسة السحاب مع الشيخ بعد نجاته من سجن باجرام - صوتي.mp3",
    "video": "اللقاء الأول لمؤسسة السحاب مع الشيخ بعد نجاته من سجن باجرام.mp4"
  },
  "221-كلمة-للشيخ-في-عمليةٍ-لاقتحامِ-أحد-مراكز-المرتدين": {
    "title": "كلمة للشيخ في عملية لاقتحام أحد مراكز المرتدين",
    "video": "اقتحام المجاهدين على معسكر للمرتدين بشماركة أبي يحيى.mp4"
  },
  "223-نورٌ-ونار-في-رثاء-الشيخ-أبي-مصعب-الزرقاوي": {
    "title": "نور ونار في رثاء الشيخ أبي مصعب الزرقاوي",
    "audio": "نور ونار.. في رثاء الشيخ أبي مصعب الزرقاوي رحمه الله - صوتي.mp3",
    "video": "نور ونار.. في رثاء الشيخ أبي مصعب الزرقاوي رحمه الله.mp4"
  },
  "226-نزال-لا-تنازل-في-رثاء-فاروق-العراقي": {
    "title": "نزال لا تنازل في رثاء فاروق العراقي",
    "audio": "نزال لا تنازل.. في رثاء فاروق العراقي - صوتي.mp3",
    "video": "نزال لا تنازل.. في رثاء فاروق العراقي.mp4"
  },
  "228-وَالَّذِينَ-يُؤْذُونَ-رَسُولَ-اللَّهِ-لَهُمْ-عَذَا": {
    "title": "﴿وَالَّذِينَ يُؤْذُونَ رَسُولَ اللَّهِ لَهُمْ عَذَابٌ أَلِيمٌ﴾",
    "audio": "تقارب الأديان خطوة جديدة ضمن الحرب الصليبية - صوتي.mp3",
    "video": "والذين يؤذون رسول الله لهم عذاب أليم.mp4"
  },
  "229-إلى-جيش-العسرة-في-الصومال": {
    "title": "إلى جيش العسرة في الصومال",
    "audio": "إلى جيش العسرة في الصومال - صوتي.mp3",
    "video": "إلى جيش العسرة في الصومال.mp4"
  },
  "231-العراق-بين-أمارات-النصر-ودسائس-المؤامرات": {
    "title": "العراق بين أمارات النصر ودسائس المؤامرات",
    "audio": "العراق بين أمارات النصر.. ودسائس المؤامرات - صوتي.mp3",
    "video": "العراق بين أمارات النصر.. ودسائس المؤامرات.mp4"
  },
  "232-الملا-داد-الله-أرجو-أن-أطأ-بعرجتي-الجنة": {
    "title": "الملا داد الله: أرجو أن أطأ بعرجتي الجنة",
    "audio": "الملا داد الله أرجو أن أطأ بعرجتي الجنة.. كلمة للشيخ في رثاء الملا داد الله رحمه الله- صوتي.mp3",
    "video": "الملا داد الله أرجو أن أطأ بعرجتي الجنة.. كلمة للشيخ في رثاء الملا داد الله رحمه الله.mp4"
  },
  "234-توحيد-آل-سعود-وتوحيد-الحق": {
    "title": "توحيد آل سعود وتوحيد الحق",
    "audio": "توحيد آل سعود وتوحيد الحق - صوتي.mp3",
    "video": "توحيد آل سعود وتوحيد الحق.mp4"
  },
  "235-محاضرةٌ-صوتية-في-فضائل-الجهاد-أُلقيت-في-أحد-معسكرا": {
    "title": "محاضرة صوتية في فضائل الجهاد",
    "audio": "محاضرة للشيخ في أحد المعسكرات.mp3"
  },
  "237-الكلمة-الختامية-للدورة-الشرعية-التي-أقيمت-في-أحد-م": {
    "title": "الكلمة الختامية للدورة الشرعية",
    "audio": "الكلمة الختامية للدورة الشرعية (طلب العلم والجهاد) - صوتي.mp3",
    "video": "الكلمة الختامية للدورة الشرعية (طلب العلم والجهاد).mp4"
  },
  "238-وتستمر-الحرب-الصليبية-أطفال-الإيدز-في-ليبيا": {
    "title": "وتستمر الحرب الصليبية - أطفال الإيدز في ليبيا",
    "audio": "أطفال الإيدز في ليبيا - صوتي.mp3",
    "video": "أطفال الإيدز في ليبيا.mp4"
  },
  "239-من-سادات-الشهداء-شهداء-جامعة-حفصة،-والشيخ-عبد-الرش": {
    "title": "من سادات الشهداء (شهداء جامعة حفصة)",
    "audio": "من سادات الشهداء - صوتي.mp3",
    "video": "من سادات الشهداء.mp4"
  },
  "240-نقاط-على-الحروف-اللقاء-الثاني-للسحاب-مع-الشيخ-بعد": {
    "title": "نقاط على الحروف - اللقاء الثاني للسحاب",
    "audio": "اللقاء الثاني لمؤسسة السحاب مع الشيخ؛ نقاط على الحروف - صوتي.mp3",
    "video": "اللقاء الثاني لمؤسسة السحاب مع الشيخ؛ نقاط على الحروف.mp4"
  },
  "243-ريح-الجنة-2": {
    "title": "ريح الجنة (2)",
    "audio": "كلمة في نهاية إصدا ريح الجنة 2.mp3"
  },
  "244-ريح-الجنة-4-وحديث-عذبٌ-عن-الشهادة-والشهداء": {
    "title": "ريح الجنة (4) - حديث عذب عن الشهادة والشهداء",
    "audio": "كلمة فى إصدار ريح الجنة 4؛ حديث عن الشهادة والشهداء.mp3"
  },
  "245-كلمة-تحريضية-مختصرة-للحركة-الإسلامية-الأوزبكية-برف": {
    "title": "كلمة تحريضية مختصرة للحركة الإسلامية الأوزبكية",
    "audio": "كلمة مختصرة للحركة الإسلامية الأوزبكية برفقة طاهر جان.mp3",
    "video": "كلمة مختصرة للحركة الإسلامية الأوزبكية برفقة طاهر جان.mp4"
  },
  "246-خطبة-عيد-الأضحى-1428": {
    "title": "خطبة عيد الأضحى «1428»",
    "audio": "خطب العيد/خطبة عيد الأضحى 1428؛ كذبوا الآن جاء القتال - صوتي.mp3",
    "video": "خطب العيد/خطبة عيد الأضحى 1428؛ كذبوا الآن جاء القتال.mp4"
  },
  "248-الأخوة-في-الله": {
    "title": "الأخوة في الله",
    "audio": "جلسات مع الشيخ في دورة الكوادر/الأخوة.mp3"
  },
  "249-التعامل-مع-أنصار-المجاهدين": {
    "title": "التعامل مع أنصار المجاهدين",
    "audio": "جلسات مع الشيخ في دورة الكوادر/الأنصار.mp3"
  },
  "250-فضل-الصحابة": {
    "title": "فضل الصحابة",
    "audios": [
      "جلسات مع الشيخ في دورة الكوادر/الصحابة 1.mp3",
      "جلسات مع الشيخ في دورة الكوادر/الصحابة 2.mp3"
    ]
  },
  "251-بمن-نبدأ-القتال؟": {
    "title": "بمن نبدأ القتال؟",
    "audio": "جلسات مع الشيخ في دورة الكوادر/بمن نبدأ القتال ؟.mp3"
  },
  "252-علو-الهمة": {
    "title": "علو الهمة",
    "audio": "جلسات مع الشيخ في دورة الكوادر/علو الهمة.mp3"
  },
  "254-رسالة-صوتية-إلى-أحد-المشايخ": {
    "title": "رسالة صوتية إلى أحد المشايخ",
    "audio": "رسالة صوتية إلى أحد المشايخ.mp3"
  },
  "255-لست-بالخب-ولا-الخب-يخدعني-ردًا-على-وثيقة-الترشيد": {
    "title": "لست بالخب ولا الخب يخدعني - ردًا على وثيقة الترشيد",
    "audio": "لست بالخب ولا الخب يخدعني.. رد على وثيقة الترشيد - صوتي.mp3",
    "video": "لست بالخب ولا الخب يخدعني.. رد على وثيقة الترشيد.mp4"
  },
  "256-الصومال-لا-سلام-بلا-إسلام": {
    "title": "الصومال.. لا سلام بلا إسلام",
    "audio": "رسالة إلى المجاهدين في الصومال؛ لا سلام بلا إسلام - صوتي.mp3",
    "video": "رسالة إلى المجاهدين في الصومال؛ لا سلام بلا إسلام.mp4"
  },
  "257-وسطية-الإسلام-ووسطية-الانهزام": {
    "title": "وسطية الإسلام ووسطية الانهزام",
    "audio": "وسطية الإسلام ووسطية الإنهزام - صوتي.mp3",
    "video": "وسطية الإسلام ووسطية الإنهزام.mp4"
  },
  "258-رفيق-الدرب-رثاء-القائد-الشهيد-أبي-الليث-الليبي--تق": {
    "title": "رفيق الدرب - رثاء الشهيد أبي الليث الليبي",
    "audio": "رفيق الدرب.. في رثاء الشيخ أبي الليث الليبي رحمه الله - صوتي.mp3",
    "video": "رفيق الدرب.. في رثاء الشيخ أبي الليث الليبي رحمه الله.mp4"
  },
  "261-النفير": {
    "title": "النفير",
    "audio": "النفير - صوتي.mp3",
    "video": "النفير.mp4"
  },
  "263-خطبة-عيد-الفطر-1429": {
    "title": "خطبة عيد الفطر «1429»",
    "audio": "خطب العيد/خطبة عيد الفطر 1429 - صوتي.mp3",
    "video": "خطب العيد/خطبة عيد الفطر 1429.mp4"
  },
  "264-تقارب-الأديان-خطوة-جديدة-ضمن-الحرب-الصليبية": {
    "title": "تقارب الأديان - خطوة جديدة ضمن الحرب الصليبية",
    "audio": "تقارب الأديان خطوة جديدة ضمن الحرب الصليبية - صوتي.mp3",
    "video": "تقارب الأديان خطوة جديدة ضمن الحرب الصليبية.mp4"
  },
  "265-خطبة-عيد-الأضحى-1429": {
    "title": "خطبة عيد الأضحى «1429»",
    "audio": "خطب العيد/خطبة عيد الأضحى 1429 - صوتي.mp3",
    "video": "خطب العيد/خطبة عيد الأضحى 1429.mp4"
  },
  "266-فلسطين-الآن-حمي-الوطيس-حول-العدوان-على-غزة": {
    "title": "فلسطين.. الآن حمي الوطيس (العدوان على غزة)",
    "audio": "فلسطين - الآن حمي الوطيس.. العدوان على غزة - صوتي.mp3",
    "video": "فلسطين - الآن حمي الوطيس.. العدوان على غزة.mp4"
  },
  "267-الصومال-إن-النصر-مع-الصبر": {
    "title": "الصومال.. إن النصر مع الصبر",
    "audio": "الصومال.. إن النصر مع الصبر - صوتي.mp3",
    "video": "الصومال.. إن النصر مع الصبر.mp4"
  },
  "268-وقفات-مع-بيان-العلماء-حول-غزَّة": {
    "title": "وقفات مع بيان العلماء حول غزة",
    "audio": "وقفات مع بيان العلماء حول غزة - صوتي.mp3",
    "video": "وقفات مع بيان العلماء حول غزة.mp4"
  },
  "272-سوات-نصرٌ-أو-شهادة": {
    "title": "سوات.. نصر أو شهادة",
    "audio": "سوات نصر أو شهادة - صوتي.mp3",
    "video": "سوات نصر أو شهادة.mp4"
  },
  "274-الصومال-وانقشعت-سحابة-الصيف": {
    "title": "الصومال.. وانقشعت سحابة الصيف",
    "audio": "الصومال.. وانقشعت سحابة الصيف - صوتي.mp3",
    "video": "الصومال.. وانقشعت سحابة الصيف.mp4"
  },
  "276-ابن-الشيخ-القبْرُ-ولا-الحَوْر": {
    "title": "ابن الشيخ.. القبر ولا الحور",
    "audio": "ابن الشيخ القبر ولا الحور - صوتي.mp3",
    "video": "ابن الشيخ القبر ولا الحور.mp4"
  },
  "277-الديمقراطية-الصنم-العصري": {
    "title": "الديمقراطية.. الصنم العصري",
    "audio": "الديمقراطية.. الصنم العصري - صوتي.mp3",
    "video": "الديمقراطية.. الصنم العصري.mp4"
  },
  "278-تُركستان-الشرقية-الجرح-المنسي": {
    "title": "تركستان الشرقية.. الجرح المنسي",
    "audio": "تركستان الشرقية.. الجرح المنسي - صوتي.mp3",
    "video": "تركستان الشرقية.. الجرح المنسي.mp4"
  },
  "281-ربح-البيع-في-فضل-الجهاد-والشهادة": {
    "title": "ربح البيع (فضل الجهاد والشهادة)",
    "audio": "ربح البيع (فضل الجهاد والشهادة) - صوتي.mp3",
    "video": "ربح البيع (فضل الجهاد والشهادة).mp4"
  },
  "282-خطبة-عيد-الفطر-1430": {
    "title": "خطبة عيد الفطر «1430»",
    "audio": "خطب العيد/خطبة عيد الفطر - 1430 - صوتي.mp3",
    "video": "خطب العيد/خطبة عيد الفطر - 1430.mp4"
  },
  "284-الجزائر-بين-تضحية-الآباء،-ووفاء-الأبناء": {
    "title": "الجزائر بين تضحية الآباء ووفاء الأبناء",
    "audio": "الجزائر بين تضحية الآباء.. ووفاء الأبناء - صوتي.mp3",
    "video": "الجزائر بين تضحية الآباء.. ووفاء الأبناء.mp4"
  },
  "285-مباحثة-في-الطائفة-الممتنعة-وقتالها": {
    "title": "مباحثة في الطائفة الممتنعة وقتالها",
    "audio": "مباحثة في مسألة «الطائفة الممتنعة» مع ثلة من مجاهدي خراسان.mp3",
    "video": "مباحثة في مسألة «الطائفة الممتنعة» مع ثلة من مجاهدي خراسان.mp4"
  },
  "286-فلسطين-صيحة-نذير،-وصرخة-تحذير": {
    "title": "فلسطين.. صيحة نذير وصرخة تحذير",
    "audio": "فلسطين صيحة نذير وصرخة تحذير - صوتي.mp3",
    "video": "فلسطين صيحة نذير وصرخة تحذير.mp4"
  },
  "384-مباحثة-في-الديمقراطية": {
    "title": "مباحثة في الديمقراطية",
    "audios": [
      "مباحثة في مسألة الديموقراطية مع ثلة من مجاهدي خراسان 1 - الجزء الأول؛ 1430 هـ.mp3",
      "مباحثة في مسألة الديموقراطية مع ثلة من مجاهدي خراسان 2 - الجزء الثاني.mp3"
    ]
  },
  "385-مباحثة-في-حقيقة-الإيمان": {
    "title": "مباحثة في حقيقة الإيمان",
    "audios": [
      "مباحثة في حقيقة الإيمان الجزء 1 الأول 1430 هـ.mp3",
      "مباحثة في حقيقة الإيمان الجزء 2 الثاني 1430 هـ.mp3",
      "مباحثة في حقيقة الإيمان الجزء 3 الثالث.mp3"
    ]
  },
  "288-بشائر-النصر-ونسائم-التمكين-خطبة-عيد-الأضحى-1430": {
    "title": "بشائر النصر ونسائم التمكين - خطبة عيد الأضحى 1430",
    "audio": "خطب العيد/خطبة عيد الأضحى 1430؛ بشائر النصر ونسائم التمكين - صوتي.mp3",
    "video": "خطب العيد/خطبة عيد الأضحى 1430؛ بشائر النصر ونسائم التمكين.mp4"
  },
  "289-رسالة-للأخوات-المهاجرات-في-ساحات-الجهاد": {
    "title": "رسالة للأخوات المهاجرات في ساحات الجهاد",
    "audio": "رسالة للأخوات المهاجرات في ساحات الجهاد - صوتي.mp3",
    "video": "رسالة للأخوات المهاجرات في ساحات الجهاد.mp4"
  },
  "290-دماءُ-قادتنا-وقودُ-معركتنا": {
    "title": "دماء قادتنا وقود معركتنا",
    "audio": "دماء قادتنا وقود معركتنا - صوتي.mp3",
    "video": "دماء قادتنا وقود معركتنا.mp4"
  },
  "291-بشائر-ونصائح-للانغماسيين-الاستشهاديين-قناديل-من-نو": {
    "title": "بشائر ونصائح للانغماسيين الاستشهاديين - قناديل من نور 7",
    "audio": "قناديل من نور 7 - بشائر ونصائح للانغماسيين الاستشهاديين.mp3",
    "video": "قناديل من نور 7 - بشائر ونصائح للانغماسيين الاستشهاديين.mp4"
  },
  "292-مسك-الشهداء-قناديل-من-نور-9": {
    "title": "مسك الشهداء - قناديل من نور 9",
    "audio": "قناديل من نور 9 - كرامات الشهداء.mp3",
    "video": "قناديل من نور 9 - كرامات الشهداء.mp4"
  },
  "293-في-رثاء-الشيخ-مصطفى-أبي-اليزيد": {
    "title": "في رثاء الشيخ مصطفى أبي اليزيد",
    "audio": "في رثاء الشيخ مصطفى أبي اليزيد - صوتي.mp3",
    "video": "في رثاء الشيخ مصطفى أبي اليزيد.mp4"
  },
  "294-عافية-صديقي-أسرٌ-وقهرٌ؛-فأين-الأبطال؟": {
    "title": "عافية صديقي.. أسر وقهر",
    "audio": "عافية صديقي أسر وقهر؛ فأين الأبطال - صوتي.mp3",
    "video": "عافية صديقي أسر وقهر؛ فأين الأبطال.mp4"
  },
  "295-عليكم-بالخنادق-قناديل-من-نور-1": {
    "title": "عليكم بالخنادق - قناديل من نور 1",
    "audio": "قناديل من نور 1 - عليكم بالخنادق.mp3",
    "video": "قناديل من نور 1 - عليكم بالخنادق.mp4"
  },
  "296-إلى-أهلنا-في-ليبيا": {
    "title": "إلى أهلنا في ليبيا",
    "audio": "إلى أهلنا في ليبيا - صوتي.mp3",
    "video": "إلى أهلنا في ليبيا.mp4"
  },
  "297-دعوة-انتقام-لشهيد-الإسلام-قناديل-من-نور-10": {
    "title": "دعوة انتقام لشهيد الإسلام - قناديل من نور 10",
    "audio": "دعوة انتقام لشهيد الإسلام.mp3",
    "video": "دعوة انتقام لشهيد الإسلام.mp4"
  },
  "298-تذكرة-رمضانية": {
    "title": "تذكرة رمضانية",
    "audio": "تذكرة رمضانية - صوتي.mp3",
    "video": "تذكرة رمضانية.mp4"
  },
  "304-الجزائر-ومعركة-الصبر": {
    "title": "الجزائر ومعركة الصبر",
    "audio": "الجزائر ومعركة الصبر - صوتي.mp3",
    "video": "الجزائر ومعركة الصبر.mp4"
  },
  "305-خطبة-عيد-الأضحى-1432هـ": {
    "title": "خطبة عيد الأضحى 1432هـ",
    "audio": "خطب العيد/خطبة عيد الأضحى 1432 - صوتي.mp3",
    "video": "خطب العيد/خطبة عيد الأضحى 1432.mp4"
  },
  "306-ليبيا-ماذا-يراد-لها؟": {
    "title": "ليبيا.. ماذا يراد لها؟",
    "audio": "ليبيا ماذا يراد لها؟ - صوتي.mp3",
    "video": "ليبيا ماذا يراد لها؟.mp4"
  },
  "307-الجيش-الأمريكي-وأخلاق-الحروب": {
    "title": "الجيش الأمريكي وأخلاق الحروب",
    "audio": "الجيش الأمريكي وأخلاق الحروب - صوتي.mp3",
    "video": "الجيش الأمريكي وأخلاق الحروب.mp4"
  },
  "308-مآسي-الشام-بين-إجرام-النصيرية-ومكائد-الغرب": {
    "title": "مآسي الشام بين إجرام النصيرية ومكائد الغرب",
    "audio": "مآسي الشام بين إجرام النصيرية ومكائد الغرب.mp3",
    "video": "مآسي الشام بين إجرام النصيرية ومكائد الغرب.mp4"
  },
  "غير-مفرغ-تفسير-سورة-الأنفال-1": {
    "title": "تفسير سورة الأنفال - المجلس 1",
    "audio": "تفسير سورة الأنفال - غير مفرغ/تفسير سورة الأنفال - المجلس 1.mp3",
    "untranscribed": true
  },
  "غير-مفرغ-تفسير-سورة-الأنفال-2": {
    "title": "تفسير سورة الأنفال - المجلس 2",
    "audio": "تفسير سورة الأنفال - غير مفرغ/تفسير سورة الأنفال - المجلس 2.mp3",
    "untranscribed": true
  },
  "غير-مفرغ-تفسير-سورة-الأنفال-3": {
    "title": "تفسير سورة الأنفال - المجلس 3",
    "audio": "تفسير سورة الأنفال - غير مفرغ/تفسير سورة الأنفال - المجلس 3.mp3",
    "untranscribed": true
  },
  "غير-مفرغ-شرح-الآجرومية-1": {
    "title": "شرح الآجرومية - الدرس الأول",
    "audio": "درسان من شرح الآجرومية - غير مفرغ/1.mp3",
    "untranscribed": true
  },
  "غير-مفرغ-شرح-الآجرومية-2": {
    "title": "شرح الآجرومية - الدرس الثاني",
    "audio": "درسان من شرح الآجرومية - غير مفرغ/2.mp3",
    "untranscribed": true
  },
  "333-القسم-الخامس-الشعر-والقصائد": {
    "title": "قصائد جهادية",
    "audio": "قصائد جهادية - صوتي.mp3",
    "video": "قصائد جهادية.mp4"
  },
  "352-أبُنَيَّ-هل-بعد-الفراق-لقاء؟": {
    "title": "قناديل من نور 13 - أبني هل بعد الفراق لقاء؟",
    "audio": "قناديل من نور 13 - أبني هل بعد الفراق لقاء؟.mp3",
    "video": "قناديل من نور 13 - أبني هل بعد الفراق لقاء؟.mp4"
  },
  "غير-مفرغ-تقرير-مراسم-العزاء": {
    "title": "تقرير عن مراسم العزاء في أسر الشيخ أبي يحيى الليبي",
    "video": "تقرير عن مراسم العزاء في أسره الشيخ أبو يحيى الليبي ويظهر صور وكتابات خاصة بالشيخ.mp4",
    "untranscribed": true
  },
  "224-كلمة-للشيخ-في-إصدار-شهداء-العيد-وعيد-الشهداء": {
    "title": "كلمة للشيخ في إصدار: «شهداء العيد وعيد الشهداء»",
    "audio": "كلمة بين اثنين من الشهداء بعد غزوة من الغزوات.mp3",
    "untranscribed": false
  },
  "1557-تعظيم-حرمة-دماء-المسلمين": {
    "title": "تعظيم حرمة دماء المسلمين",
    "audio": "تعظيم حرمة دماء المسلمين - صوتي.mp3",
    "video": "تعظيم حرمة دماء المسلمين - مرئي.mp4"
  },
  "1561-تحية-لأهلنا-في-ليبيا": {
    "title": "تحية لأهلنا في ليبيا",
    "audio": "تحية لأهلنا في ليبيا - صوتي.mp3",
    "video": "تحية لأهلنا في ليبيا - مرئي.mp4"
  },
  "1564-بشائر-النصـر-في-شهر-الصبر": {
    "title": "بشائر النصر في شهر الصبر",
    "audio": "بشائر النصر في شهر الصبر - صوتي.mp3",
    "video": "بشائر النصر في شهر الصبر - مرئي.mp4"
  },
  "1573-درس-في-التحريض-على-الجهاد": {
    "title": "درس في التحريض على الجهاد",
    "audio": "درس في التحريض على الجهاد.mp3"
  },
  "1735-التجربة-الجزائرية": {
    "title": "التجربة الجزائرية",
    "audio": "التجربة الجزائرية.mp3"
  },
  "1769-شرح-حديث-المؤمن-القوي-خير-وأحب-إلى-الله-من-الم": {
    "title": "شرح حديث: (المؤمن القوي خير وأحب إلى الله من المؤمن الضعيف)",
    "audio": "شرح حديث المؤمن القوي.mp3"
  },
  "1799-أسباب-النصر": {
    "title": "أسباب النصر",
    "audio": "أسباب النصر.mp3"
  },
  "1810-مقاصد-الجهاد": {
    "title": "مقاصد الجهاد",
    "audio": "مقاصد الجهاد.mp3"
  },
  "1852-قراءة-في-كتاب-مختصر-منهاج-القاصدين؛-فصل-العزلة-وال": {
    "title": "قراءة في كتاب مختصر منهاج القاصدين؛ فصل العزلة والاختلاط",
    "audio": "قراءة في كتاب مختصر منهاج القاصدين - فصل في العزلة والاختلاط.mp3"
  },
  "1860-الهداية-ونعمة-الجهاد": {
    "title": "الهداية ونعمة الجهاد - قناديل من نور 6",
    "audio": "الهداية ونعمة الجهاد - قناديل من نور 6.mp3",
    "video": "الهداية ونعمة الجهاد - قناديل من نور 6.mp4"
  },
  "1870-أهل-التجارة-مع-الله": {
    "title": "أهل التجارة مع الله - قناديل من نور 11",
    "audio": "أهل التجارة مع الله؛ التائبون العابدون الحامدون.mp3",
    "video": "أهل التجارة مع الله؛ التائبون العابدون الحامدون.mp4"
  },
  "1896-هلاك-الأمم-الظالمة-رسالة-إلى-الحكام-الجدد": {
    "title": "هلاك الأمم الظالمة.. رسالة إلى الحكام الجدد",
    "audio": "هلاك الأمم الظالمة.. رسالة إلى الحكام الجدد.mp3"
  },
  "912-الدرس-الثاني": {
    "title": "سلسلة الثقافة الإسلامية والوعي - الدرس الثاني: الحق - الدين",
    "audio": "سلسلة الثقافة والوعي/الثقافة والوعي 2 - الحق - الدين.mp3"
  },
  "915-الدرس-الثالث": {
    "title": "سلسلة الثقافة الإسلامية والوعي - الدرس الثالث: الابتلاء والاختبار والفتنة والامتحان",
    "audio": "سلسلة الثقافة والوعي/الثقافة والوعي 3 - الابتلاء والإختبار والإمتحان والفتنة.mp3"
  },
  "920-الدرس-الخامس": {
    "title": "سلسلة الثقافة الإسلامية والوعي - الدرس الخامس: الجهاد والدعوة",
    "audio": "سلسلة الثقافة والوعي/الثقافة والوعي 5 - الجهاد والدعوة.mp3"
  }
}